GraficImageProcessig/__init__.py
GraficImageProcessig/gip.py
GraficImageProcessig/test.py
GraficImageProcessig-0.0.7.dist-info/LICENSE
GraficImageProcessig-0.0.7.dist-info/METADATA
GraficImageProcessig-0.0.7.dist-info/WHEEL
GraficImageProcessig-0.0.7.dist-info/top_level.txt
GraficImageProcessig-0.0.7.dist-info/RECORD
